acttrader/__init__.py
acttrader/client.py
acttrader/digest_auth.py
acttrader/main.py
acttrader/symbol_cache.py
acttrader/types.py
acttrader/modules/__init__.py
acttrader/modules/account.py
acttrader/modules/alert.py
acttrader/modules/auth.py
acttrader/modules/market.py
acttrader/modules/streaming.py
acttrader/modules/trading.py
acttrader_trading_sdk-1.0.1.dist-info/licenses/LICENSE
tests/__init__.py
tests/test_client.py
tests/test_types.py
acttrader_trading_sdk-1.0.1.dist-info/METADATA
acttrader_trading_sdk-1.0.1.dist-info/WHEEL
acttrader_trading_sdk-1.0.1.dist-info/top_level.txt
acttrader_trading_sdk-1.0.1.dist-info/RECORD
