Metadata-Version: 2.4
Name: acttrader-trading-sdk
Version: 1.0.1
Summary: Official Python SDK for ActTrader Trading API
Home-page: https://github.com/acttrader/python-trading-sdk
Author: Act
Author-email: support@acttrader.com
Project-URL: Homepage, https://github.com/acttrader/python-sdk
Project-URL: Bug Reports, https://github.com/acttrader/python-sdk/issues
Project-URL: Source, https://github.com/acttrader/python-sdk
Project-URL: Documentation, https://github.com/acttrader/python-sdk#readme
Keywords: acttrader,trading,forex,api,sdk,trading-api,market-data,websocket,financial,broker
Classifier: Development Status :: 5 - Production/Stable
Classifier: Intended Audience :: Developers
Classifier: License :: OSI Approved :: ISC License (ISCL)
Classifier: Operating System :: OS Independent
Classifier: Programming Language :: Python :: 3
Classifier: Programming Language :: Python :: 3.8
Classifier: Programming Language :: Python :: 3.9
Classifier: Programming Language :: Python :: 3.10
Classifier: Programming Language :: Python :: 3.11
Classifier: Programming Language :: Python :: 3.12
Classifier: Topic :: Office/Business :: Financial :: Investment
Classifier: Topic :: Software Development :: Libraries :: Python Modules
Requires-Python: >=3.8
License-File: LICENSE
Requires-Dist: requests>=2.28.0
Requires-Dist: websockets>=11.0.0
Requires-Dist: aiohttp>=3.8.0
Requires-Dist: asyncio-mqtt>=0.13.0
Requires-Dist: pydantic>=2.0.0
Requires-Dist: typing-extensions>=4.0.0
Requires-Dist: requests-ntlm>=1.2.0
Requires-Dist: python-dateutil>=2.8.0
Requires-Dist: ujson>=5.0.0
Provides-Extra: dev
Requires-Dist: pytest>=7.0.0; extra == "dev"
Requires-Dist: pytest-asyncio>=0.21.0; extra == "dev"
Requires-Dist: black>=22.0.0; extra == "dev"
Requires-Dist: flake8>=5.0.0; extra == "dev"
Requires-Dist: mypy>=1.0.0; extra == "dev"
Dynamic: author
Dynamic: author-email
Dynamic: classifier
Dynamic: description
Dynamic: description-content-type
Dynamic: home-page
Dynamic: keywords
Dynamic: license-file
Dynamic: project-url
Dynamic: provides-extra
Dynamic: requires-dist
Dynamic: requires-python
Dynamic: summary
